{
  "registrations": [
    {
      "admissionDate": "22/10/2023",
      "email": "luiz@caju.com.br",
      "employeeName": "Luiz Filho",
      "status": "APROVED",
      "cpf": "56642105087",
      "id": "3"
    },
    {
      "id": "1",
      "admissionDate": "22/10/2023",
      "email": "filipe@caju.com.br",
      "employeeName": "Filipe Marins",
      "status": "REPROVED",
      "cpf": "78502270001"
    },
    {
      "id": "2",
      "admissionDate": "22/10/2023",
      "email": "jose@caju.com.br",
      "employeeName": "José Leão",
      "status": "REVIEW",
      "cpf": "78502270001"
    },
    {
      "id": "9791",
      "status": "REVIEW",
      "employeeName": "Pedro Henrick",
      "email": "pedro.henrickcs@gmail.com",
      "cpf": "228.504.028-85",
      "admissionDate": "2024-04-01"
    }
  ]
}